{
    "database_id": 222,
    "label": "WWA-02",
    "manufacturer_name": "FortrezZ LLC",
    "manufacturer_id": "0084",
    "device_ref": [
        "0061:010C",
        "0063:010C"
    ],
    "version_min": 0,
    "version_max": 255.255,
    "decription": "Wireless Water and Temperature Alarm",
    "overview": "",
    "inclusion": "",
    "exclusion": "",
    "wakeup": "",
    "protocol_version": 2.097,
    "listening": false,
    "frequently_listening": false,
    "routing": true,
    "beaming": true,
    "library_type": {
        "id": 7,
        "name": "LIB_CONTROLLER_BRIDGE"
    },
    "basic_class": {
        "id": 4,
        "name": "BASIC_TYPE_ROUTING_SLAVE"
    },
    "generic_class": {
        "id": 4,
        "name": "GENERIC_TYPE_SENSOR_MULTILEVEL"
    },
    "specific_class": {
        "id": 4,
        "name": "SPECIFIC_TYPE_ROUTING_SENSOR_MULTILEVEL"
    },
    "endpoints": [
        {
            "id": 0,
            "basic_class": {
                "id": 4,
                "name": "BASIC_TYPE_ROUTING_SLAVE"
            },
            "generic_class": {
                "id": 33,
                "name": "GENERIC_TYPE_SENSOR_MULTILEVEL"
            },
            "specific_class": {
                "id": 1,
                "name": "SPECIFIC_TYPE_ROUTING_SENSOR_MULTILEVEL"
            },
            "commandclasses": [
                {
                    "id": "00",
                    "name": "NO_OPERATION",
                    "version": "1",
                    "nif": false,
                    "basic": false,
                    "secure": false,
                    "nonsecure": true,
                    "config": "",
                    "channels": []
                },
                {
                    "id": "20",
                    "name": "BASIC",
                    "version": "1",
                    "nif": false,
                    "basic": false,
                    "secure": false,
                    "nonsecure": true,
                    "config": "",
                    "channels": []
                },
                {
                    "id": "31",
                    "name": "SENSOR_MULTILEVEL",
                    "version": "1",
                    "nif": false,
                    "basic": false,
                    "secure": false,
                    "nonsecure": true,
                    "config": "",
                    "channels": [
                        {
                            "type": "sensor_temperature",
                            "label": "Sensor (temperature)",
                            "config": [
                                "type=TEMPERATURE"
                            ]
                        }
                    ]
                },
                {
                    "id": "70",
                    "name": "CONFIGURATION",
                    "version": "1",
                    "nif": false,
                    "basic": false,
                    "secure": false,
                    "nonsecure": true,
                    "config": "",
                    "channels": []
                },
                {
                    "id": "71",
                    "name": "ALARM",
                    "version": "1",
                    "nif": false,
                    "basic": false,
                    "secure": false,
                    "nonsecure": true,
                    "config": "",
                    "channels": [
                        {
                            "type": "alarm_flood",
                            "label": "Alarm",
                            "config": [
                                "type=GENERAL"
                            ]
                        }
                    ]
                },
                {
                    "id": "72",
                    "name": "MANUFACTURER_SPECIFIC",
                    "version": "1",
                    "nif": false,
                    "basic": false,
                    "secure": false,
                    "nonsecure": true,
                    "config": "",
                    "channels": []
                },
                {
                    "id": "80",
                    "name": "BATTERY",
                    "version": "1",
                    "nif": false,
                    "basic": false,
                    "secure": false,
                    "nonsecure": true,
                    "config": "",
                    "channels": []
                },
                {
                    "id": "84",
                    "name": "WAKE_UP",
                    "version": "2",
                    "nif": false,
                    "basic": false,
                    "secure": false,
                    "nonsecure": true,
                    "config": "",
                    "channels": []
                },
                {
                    "id": "85",
                    "name": "ASSOCIATION",
                    "version": "1",
                    "nif": false,
                    "basic": false,
                    "secure": false,
                    "nonsecure": true,
                    "config": "",
                    "channels": []
                },
                {
                    "id": "86",
                    "name": "VERSION",
                    "version": "1",
                    "nif": false,
                    "basic": false,
                    "secure": false,
                    "nonsecure": true,
                    "config": "",
                    "channels": []
                }
            ]
        }
    ],
    "parameters": [
        {
            "id": 1,
            "label": "Low Temperature Trigger Point",
            "description": "",
            "overview": "",
            "size": 1,
            "bitmask": "00000000",
            "default": 4,
            "read_only": false,
            "write_only": false,
            "value_min": 0,
            "value_max": 255,
            "options": []
        },
        {
            "id": 2,
            "label": "High Temperature Trigger Point",
            "description": "",
            "overview": "",
            "size": 1,
            "bitmask": "00000000",
            "default": 70,
            "read_only": false,
            "write_only": false,
            "value_min": 0,
            "value_max": 255,
            "options": []
        }
    ],
    "associations": [
        {
            "id": 1,
            "label": "Water and Temperature Alarms",
            "max_nodes": 5,
            "controller": true,
            "description": "",
            "overview": ""
        },
        {
            "id": 2,
            "label": "Water Alarms",
            "max_nodes": 5,
            "controller": false,
            "description": "",
            "overview": ""
        },
        {
            "id": 3,
            "label": "Temperature Alarms",
            "max_nodes": 5,
            "controller": false,
            "description": "",
            "overview": ""
        }
    ]
}