{
    "database_id": 59,
    "label": "5082xx",
    "manufacturer_name": "Merten",
    "manufacturer_id": "007A",
    "device_ref": [
        "0002:0001"
    ],
    "version_min": 0,
    "version_max": 255.255,
    "decription": "Battery Powered Wall Controller MOVE",
    "overview": "",
    "inclusion": "",
    "exclusion": "",
    "wakeup": "",
    "protocol_version": 2.027,
    "listening": false,
    "frequently_listening": false,
    "routing": false,
    "beaming": false,
    "library_type": {
        "id": 2,
        "name": "LIB_CONTROLLER"
    },
    "basic_class": {
        "id": 1,
        "name": "BASIC_TYPE_CONTROLLER"
    },
    "generic_class": {
        "id": 1,
        "name": "GENERIC_TYPE_SWITCH_REMOTE"
    },
    "specific_class": {
        "id": 1,
        "name": null
    },
    "endpoints": [
        {
            "id": 0,
            "basic_class": {
                "id": 1,
                "name": "BASIC_TYPE_CONTROLLER"
            },
            "generic_class": {
                "id": 18,
                "name": "GENERIC_TYPE_SWITCH_REMOTE"
            },
            "specific_class": {
                "id": 0,
                "name": null
            },
            "commandclasses": [
                {
                    "id": "00",
                    "name": "NO_OPERATION",
                    "version": "1",
                    "nif": false,
                    "basic": false,
                    "secure": false,
                    "nonsecure": true,
                    "config": "",
                    "channels": []
                },
                {
                    "id": "20",
                    "name": "BASIC",
                    "version": "1",
                    "nif": false,
                    "basic": false,
                    "secure": false,
                    "nonsecure": true,
                    "config": "",
                    "channels": [
                        {
                            "type": "switch_binary",
                            "label": "Switch",
                            "config": []
                        }
                    ]
                },
                {
                    "id": "70",
                    "name": "CONFIGURATION",
                    "version": "1",
                    "nif": true,
                    "basic": false,
                    "secure": false,
                    "nonsecure": true,
                    "config": "",
                    "channels": []
                },
                {
                    "id": "72",
                    "name": "MANUFACTURER_SPECIFIC",
                    "version": "1",
                    "nif": true,
                    "basic": false,
                    "secure": false,
                    "nonsecure": true,
                    "config": "",
                    "channels": []
                },
                {
                    "id": "85",
                    "name": "ASSOCIATION",
                    "version": "1",
                    "nif": true,
                    "basic": false,
                    "secure": false,
                    "nonsecure": true,
                    "config": "",
                    "channels": []
                },
                {
                    "id": "86",
                    "name": "VERSION",
                    "version": "1",
                    "nif": true,
                    "basic": false,
                    "secure": false,
                    "nonsecure": true,
                    "config": "",
                    "channels": []
                },
                {
                    "id": "8E",
                    "name": "MULTI_INSTANCE_ASSOCIATION",
                    "version": "1",
                    "nif": true,
                    "basic": false,
                    "secure": false,
                    "nonsecure": true,
                    "config": "",
                    "channels": []
                }
            ]
        }
    ],
    "parameters": [
        {
            "id": 4,
            "label": "Switching single-surface",
            "description": "",
            "overview": "",
            "size": 1,
            "bitmask": "00000000",
            "default": 0,
            "read_only": false,
            "write_only": false,
            "value_min": 0,
            "value_max": 127,
            "options": []
        },
        {
            "id": 44,
            "label": "Doorbell function",
            "description": "",
            "overview": "",
            "size": 1,
            "bitmask": "00000000",
            "default": 0,
            "read_only": false,
            "write_only": false,
            "value_min": 0,
            "value_max": 127,
            "options": []
        },
        {
            "id": 52,
            "label": "LOWER shutter as long as button is pressed",
            "description": "Direction of movement changes after each switching process",
            "overview": "",
            "size": 1,
            "bitmask": "00000000",
            "default": 0,
            "read_only": false,
            "write_only": false,
            "value_min": 0,
            "value_max": 127,
            "options": []
        },
        {
            "id": 54,
            "label": "Move shutter single-surface",
            "description": "",
            "overview": "",
            "size": 1,
            "bitmask": "00000000",
            "default": 0,
            "read_only": false,
            "write_only": false,
            "value_min": 0,
            "value_max": 127,
            "options": []
        },
        {
            "id": 55,
            "label": "RAISE shutter as long as button is pressed",
            "description": "",
            "overview": "",
            "size": 1,
            "bitmask": "00000000",
            "default": 0,
            "read_only": false,
            "write_only": false,
            "value_min": 0,
            "value_max": 127,
            "options": []
        }
    ],
    "associations": [
        {
            "id": 1,
            "label": "Button",
            "max_nodes": 12,
            "controller": true,
            "description": "",
            "overview": ""
        }
    ]
}