{
    "database_id": 49,
    "label": "swiidplug",
    "manufacturer_name": "Reitz-Group.de",
    "manufacturer_id": "0064",
    "device_ref": [
        "0166:2007"
    ],
    "version_min": 0,
    "version_max": 255.255,
    "decription": "SwiidPlug",
    "overview": "<p>The SwiidPlug\u2122 is designed to switch on and off remotely appliances (mainly lights) which are plugged into its female socket, The SwiidPlug\u2122 is suitable for the wireless switching of incandescent light bulbs as well as halogen and LED lights (all transformer types). The SwiidPlug\u2122 can be operated manually by pressing on its FUNCTION button which then acts as an on\/off toggle switch and can be operated remotely and wirelessly by Z -Wave\u00ae. The SwiidPlug\u2122 can also handle associations with other devices, both ways to and from it. Thus, your SwiidPlug\u2122 can respond directly to a signal from another Z-Wave\u00ae device in your network, such as the triggering of a presence detector. As soon as it has been plugged into a mains socket, the SwiidPlug\u2122 can be included into a Z-Wave\u00ae network so as to interoperate with controllers and other Z-Wave\u00ae devices.\u00a0<\/p> <p>http:\/\/www.swiid.com\/medias\/documents\/ZAP-User-s-manual-vBAT-30.11.2014.pdf<\/p> <p>http:\/\/www.swiid.com\/medias\/documents\/advanced-swiidplug.pdf\u00a0<\/p>",
    "inclusion": "",
    "exclusion": "",
    "wakeup": "",
    "protocol_version": 1.21,
    "listening": true,
    "frequently_listening": false,
    "routing": true,
    "beaming": true,
    "library_type": {
        "id": 7,
        "name": "LIB_CONTROLLER_BRIDGE"
    },
    "basic_class": {
        "id": 4,
        "name": "BASIC_TYPE_ROUTING_SLAVE"
    },
    "generic_class": {
        "id": 4,
        "name": "GENERIC_TYPE_SWITCH_BINARY"
    },
    "specific_class": {
        "id": 4,
        "name": "SPECIFIC_TYPE_POWER_SWITCH_BINARY"
    },
    "endpoints": [
        {
            "id": 0,
            "basic_class": {
                "id": 4,
                "name": "BASIC_TYPE_ROUTING_SLAVE"
            },
            "generic_class": {
                "id": 16,
                "name": "GENERIC_TYPE_SWITCH_BINARY"
            },
            "specific_class": {
                "id": 1,
                "name": "SPECIFIC_TYPE_POWER_SWITCH_BINARY"
            },
            "commandclasses": [
                {
                    "id": "00",
                    "name": "NO_OPERATION",
                    "version": "1",
                    "nif": false,
                    "basic": false,
                    "secure": false,
                    "nonsecure": true,
                    "config": "",
                    "channels": []
                },
                {
                    "id": "20",
                    "name": "BASIC",
                    "version": "1",
                    "nif": false,
                    "basic": false,
                    "secure": false,
                    "nonsecure": true,
                    "config": "",
                    "channels": []
                },
                {
                    "id": "25",
                    "name": "SWITCH_BINARY",
                    "version": "1",
                    "nif": true,
                    "basic": true,
                    "secure": false,
                    "nonsecure": true,
                    "config": "",
                    "channels": [
                        {
                            "type": "switch_binary",
                            "label": "Switch",
                            "config": []
                        }
                    ]
                },
                {
                    "id": "27",
                    "name": "SWITCH_ALL",
                    "version": "1",
                    "nif": true,
                    "basic": false,
                    "secure": false,
                    "nonsecure": true,
                    "config": "",
                    "channels": []
                },
                {
                    "id": "72",
                    "name": "MANUFACTURER_SPECIFIC",
                    "version": "1",
                    "nif": true,
                    "basic": false,
                    "secure": false,
                    "nonsecure": true,
                    "config": "",
                    "channels": []
                },
                {
                    "id": "75",
                    "name": "PROTECTION",
                    "version": "1",
                    "nif": true,
                    "basic": false,
                    "secure": false,
                    "nonsecure": true,
                    "config": "",
                    "channels": []
                },
                {
                    "id": "82",
                    "name": "HAIL",
                    "version": "1",
                    "nif": true,
                    "basic": false,
                    "secure": false,
                    "nonsecure": true,
                    "config": "",
                    "channels": []
                },
                {
                    "id": "86",
                    "name": "VERSION",
                    "version": "1",
                    "nif": true,
                    "basic": false,
                    "secure": false,
                    "nonsecure": true,
                    "config": "",
                    "channels": []
                },
                {
                    "id": "87",
                    "name": "INDICATOR",
                    "version": "1",
                    "nif": true,
                    "basic": false,
                    "secure": false,
                    "nonsecure": true,
                    "config": "",
                    "channels": []
                }
            ]
        }
    ],
    "parameters": [],
    "associations": []
}