{
    "database_id": 522,
    "label": "Siren Alarm",
    "manufacturer_name": "Shenzhen Neo Electronics Co., Ltd",
    "manufacturer_id": "0258",
    "device_ref": [
        "0003:1088"
    ],
    "version_min": 0,
    "version_max": 255.255,
    "decription": "Siren Alarm",
    "overview": "",
    "inclusion": "",
    "exclusion": "",
    "wakeup": "",
    "protocol_version": 4.034,
    "listening": false,
    "frequently_listening": true,
    "routing": true,
    "beaming": false,
    "library_type": {
        "id": 7,
        "name": "LIB_CONTROLLER_BRIDGE"
    },
    "basic_class": {
        "id": 4,
        "name": "BASIC_TYPE_ROUTING_SLAVE"
    },
    "generic_class": {
        "id": 4,
        "name": "GENERIC_TYPE_SWITCH_BINARY"
    },
    "specific_class": {
        "id": 4,
        "name": "SPECIFIC_TYPE_SIREN"
    },
    "endpoints": [
        {
            "id": 0,
            "basic_class": {
                "id": 4,
                "name": "BASIC_TYPE_ROUTING_SLAVE"
            },
            "generic_class": {
                "id": 16,
                "name": "GENERIC_TYPE_SWITCH_BINARY"
            },
            "specific_class": {
                "id": 5,
                "name": "SPECIFIC_TYPE_SIREN"
            },
            "commandclasses": [
                {
                    "id": "00",
                    "name": "NO_OPERATION",
                    "version": "1",
                    "nif": false,
                    "basic": false,
                    "secure": false,
                    "nonsecure": true,
                    "config": "",
                    "channels": []
                },
                {
                    "id": "20",
                    "name": "BASIC",
                    "version": "1",
                    "nif": false,
                    "basic": false,
                    "secure": false,
                    "nonsecure": true,
                    "config": "",
                    "channels": []
                },
                {
                    "id": "25",
                    "name": "SWITCH_BINARY",
                    "version": "1",
                    "nif": false,
                    "basic": false,
                    "secure": false,
                    "nonsecure": true,
                    "config": "",
                    "channels": [
                        {
                            "type": "switch_binary",
                            "label": "Switch",
                            "config": []
                        }
                    ]
                },
                {
                    "id": "70",
                    "name": "CONFIGURATION",
                    "version": "1",
                    "nif": false,
                    "basic": false,
                    "secure": false,
                    "nonsecure": true,
                    "config": "",
                    "channels": []
                },
                {
                    "id": "71",
                    "name": "ALARM",
                    "version": "1",
                    "nif": false,
                    "basic": false,
                    "secure": false,
                    "nonsecure": true,
                    "config": "",
                    "channels": [
                        {
                            "type": "alarm_general",
                            "label": "Alarm",
                            "config": []
                        }
                    ]
                },
                {
                    "id": "72",
                    "name": "MANUFACTURER_SPECIFIC",
                    "version": "1",
                    "nif": false,
                    "basic": false,
                    "secure": false,
                    "nonsecure": true,
                    "config": "",
                    "channels": []
                },
                {
                    "id": "80",
                    "name": "BATTERY",
                    "version": "1",
                    "nif": false,
                    "basic": false,
                    "secure": false,
                    "nonsecure": true,
                    "config": "",
                    "channels": []
                },
                {
                    "id": "85",
                    "name": "ASSOCIATION",
                    "version": "1",
                    "nif": false,
                    "basic": false,
                    "secure": false,
                    "nonsecure": true,
                    "config": "",
                    "channels": []
                },
                {
                    "id": "86",
                    "name": "VERSION",
                    "version": "1",
                    "nif": false,
                    "basic": false,
                    "secure": false,
                    "nonsecure": true,
                    "config": "",
                    "channels": []
                }
            ]
        }
    ],
    "parameters": [
        {
            "id": 1,
            "label": "Configure Alarm music volume",
            "description": "Configure Alarm music volume",
            "overview": "",
            "size": 1,
            "bitmask": "00000000",
            "default": 2,
            "read_only": false,
            "write_only": false,
            "value_min": 1,
            "value_max": 3,
            "options": []
        },
        {
            "id": 2,
            "label": "Alarm music duration time",
            "description": "Alarm music duration time",
            "overview": "",
            "size": 1,
            "bitmask": "00000000",
            "default": 2,
            "read_only": false,
            "write_only": false,
            "value_min": 0,
            "value_max": 255,
            "options": []
        },
        {
            "id": 3,
            "label": "Door bell music duration time",
            "description": "Door bell music duration time",
            "overview": "",
            "size": 1,
            "bitmask": "00000000",
            "default": 1,
            "read_only": false,
            "write_only": false,
            "value_min": 0,
            "value_max": 255,
            "options": []
        },
        {
            "id": 4,
            "label": "Door bell music volume",
            "description": "Door bell music volume",
            "overview": "",
            "size": 1,
            "bitmask": "00000000",
            "default": 2,
            "read_only": false,
            "write_only": false,
            "value_min": 1,
            "value_max": 3,
            "options": []
        },
        {
            "id": 5,
            "label": "Alarm music index",
            "description": "Alarm music index",
            "overview": "",
            "size": 1,
            "bitmask": "00000000",
            "default": 9,
            "read_only": false,
            "write_only": false,
            "value_min": 1,
            "value_max": 10,
            "options": []
        },
        {
            "id": 6,
            "label": "Door bell music index",
            "description": "Door bell music index",
            "overview": "",
            "size": 1,
            "bitmask": "00000000",
            "default": 10,
            "read_only": false,
            "write_only": false,
            "value_min": 1,
            "value_max": 10,
            "options": []
        },
        {
            "id": 7,
            "label": "Default Siren on mode",
            "description": "Default Siren on mode",
            "overview": "<p>This parameter defines the default music index, volume and duration time for siren on.<\/p> <p>This parameter can be selected between ALARM MUSIC and DOOR BELL music.<\/p> <p>The settings for ALARM MUSIC defines by Param #1, #2, #5.<\/p> <p>The settings for DOOR BELL defines by Param #3, #4, #6.<\/p>",
            "size": 1,
            "bitmask": "00000000",
            "default": 1,
            "read_only": false,
            "write_only": false,
            "value_min": 1,
            "value_max": 2,
            "options": []
        }
    ],
    "associations": [
        {
            "id": 1,
            "label": "Group 1",
            "max_nodes": 5,
            "controller": true,
            "description": "",
            "overview": ""
        },
        {
            "id": 2,
            "label": "Group 2",
            "max_nodes": 5,
            "controller": true,
            "description": "",
            "overview": ""
        },
        {
            "id": 3,
            "label": "Group2",
            "max_nodes": 5,
            "controller": true,
            "description": "",
            "overview": ""
        }
    ]
}