{
    "database_id": 104,
    "label": "ZP3102",
    "manufacturer_name": "Vision Security",
    "manufacturer_id": "0109",
    "device_ref": [
        "2002:0201",
        "2002:0202",
        "2002:0203",
        "2002:0204",
        "2002:0205"
    ],
    "version_min": 0,
    "version_max": 7.99,
    "decription": "Motion Sensor",
    "overview": "",
    "inclusion": "",
    "exclusion": "",
    "wakeup": "",
    "protocol_version": 3.052,
    "listening": false,
    "frequently_listening": false,
    "routing": true,
    "beaming": true,
    "library_type": {
        "id": 6,
        "name": "LIB_SLAVE_ROUTING"
    },
    "basic_class": {
        "id": 4,
        "name": "BASIC_TYPE_ROUTING_SLAVE"
    },
    "generic_class": {
        "id": 4,
        "name": "GENERIC_TYPE_SENSOR_BINARY"
    },
    "specific_class": {
        "id": 4,
        "name": "SPECIFIC_TYPE_ROUTING_SENSOR_BINARY"
    },
    "endpoints": [
        {
            "id": 0,
            "basic_class": {
                "id": 4,
                "name": "BASIC_TYPE_ROUTING_SLAVE"
            },
            "generic_class": {
                "id": 32,
                "name": "GENERIC_TYPE_SENSOR_BINARY"
            },
            "specific_class": {
                "id": 1,
                "name": "SPECIFIC_TYPE_ROUTING_SENSOR_BINARY"
            },
            "commandclasses": [
                {
                    "id": "00",
                    "name": "NO_OPERATION",
                    "version": "1",
                    "nif": false,
                    "basic": false,
                    "secure": false,
                    "nonsecure": true,
                    "config": "",
                    "channels": []
                },
                {
                    "id": "20",
                    "name": "BASIC",
                    "version": "1",
                    "nif": false,
                    "basic": false,
                    "secure": false,
                    "nonsecure": true,
                    "config": "",
                    "channels": []
                },
                {
                    "id": "30",
                    "name": "SENSOR_BINARY",
                    "version": "1",
                    "nif": false,
                    "basic": true,
                    "secure": false,
                    "nonsecure": true,
                    "config": "",
                    "channels": [
                        {
                            "type": "sensor_binary",
                            "label": "Binary Sensor",
                            "config": []
                        }
                    ]
                },
                {
                    "id": "31",
                    "name": "SENSOR_MULTILEVEL",
                    "version": "4",
                    "nif": false,
                    "basic": false,
                    "secure": false,
                    "nonsecure": true,
                    "config": "",
                    "channels": [
                        {
                            "type": "sensor_temperature",
                            "label": "Sensor (temperature)",
                            "config": [
                                "type=TEMPERATURE"
                            ]
                        }
                    ]
                },
                {
                    "id": "70",
                    "name": "CONFIGURATION",
                    "version": "1",
                    "nif": false,
                    "basic": false,
                    "secure": false,
                    "nonsecure": true,
                    "config": "",
                    "channels": []
                },
                {
                    "id": "71",
                    "name": "ALARM",
                    "version": "1",
                    "nif": false,
                    "basic": false,
                    "secure": false,
                    "nonsecure": true,
                    "config": "",
                    "channels": [
                        {
                            "type": "alarm_burglar",
                            "label": "Alarm (burglar)",
                            "config": [
                                "type=BURGLAR"
                            ]
                        }
                    ]
                },
                {
                    "id": "72",
                    "name": "MANUFACTURER_SPECIFIC",
                    "version": "1",
                    "nif": false,
                    "basic": false,
                    "secure": false,
                    "nonsecure": true,
                    "config": "",
                    "channels": []
                },
                {
                    "id": "80",
                    "name": "BATTERY",
                    "version": "1",
                    "nif": false,
                    "basic": false,
                    "secure": false,
                    "nonsecure": true,
                    "config": "",
                    "channels": []
                },
                {
                    "id": "84",
                    "name": "WAKE_UP",
                    "version": "2",
                    "nif": false,
                    "basic": false,
                    "secure": false,
                    "nonsecure": true,
                    "config": "",
                    "channels": []
                },
                {
                    "id": "85",
                    "name": "ASSOCIATION",
                    "version": "1",
                    "nif": false,
                    "basic": false,
                    "secure": false,
                    "nonsecure": true,
                    "config": "",
                    "channels": []
                },
                {
                    "id": "86",
                    "name": "VERSION",
                    "version": "1",
                    "nif": false,
                    "basic": false,
                    "secure": false,
                    "nonsecure": true,
                    "config": "",
                    "channels": []
                }
            ]
        }
    ],
    "parameters": [
        {
            "id": 1,
            "label": "On time in minutes",
            "description": "Delay before sending OFF",
            "overview": "",
            "size": 1,
            "bitmask": "00000000",
            "default": 3,
            "read_only": false,
            "write_only": false,
            "value_min": 1,
            "value_max": 255,
            "options": []
        },
        {
            "id": 2,
            "label": "Celsius \/ Fahrenheit",
            "description": "0 = Celsius, 1 = Fahrenheit",
            "overview": "",
            "size": 1,
            "bitmask": "00000000",
            "default": 0,
            "read_only": false,
            "write_only": false,
            "value_min": 0,
            "value_max": 1,
            "options": [
                {
                    "value": 0,
                    "label": "Celsius"
                },
                {
                    "value": 1,
                    "label": "Fahrenheit"
                }
            ]
        },
        {
            "id": 3,
            "label": "Infrared sensor sensitivity adjustment",
            "description": "1 is most sensitive, 7 is least",
            "overview": "<p>(Parameter 3) Infrared sensor sensitivity adjustment, 7 levels sensitivity, 1 = most<br \/>sensitive, 7 = most insensitive, default values= 4<\/p>",
            "size": 1,
            "bitmask": "00000000",
            "default": 4,
            "read_only": false,
            "write_only": false,
            "value_min": 1,
            "value_max": 7,
            "options": []
        }
    ],
    "associations": [
        {
            "id": 1,
            "label": "Control Command",
            "max_nodes": 5,
            "controller": true,
            "description": "",
            "overview": ""
        }
    ]
}