<?xml version="1.0" encoding="utf-8"?>
<ZWaveDevice xmlns="http://www.pepper1.net/zwavedb/xml-schemata/z-wave" schemaVersion="2">

	<descriptorVersion>1</descriptorVersion>

	<deviceData>
		<manufacturerId value="010f"/>
		<productType value="0403"/>
		<productId value="1000"/>
		<libType value="00"/>
		<protoVersion value="00"/>
		<protoSubVersion value="00"/>
		<appVersion value="00"/>
		<appSubVersion value="00"/>
		<basicClass value="04"/>
		<genericClass value="10"/>
		<specificClass value="01"/>
		<optional value="true"/>
		<listening value="true"/>
		<routing value="true"/>
		<beamSensor>0</beamSensor>
		<rfFrequency>EU</rfFrequency>

	</deviceData>

	<deviceDescription>
		<description>
			<lang xml:lang="en">Single Relay Switch 2 FGS-213</lang>
		</description>
		<wakeupNote>
			<lang xml:lang="en"></lang>
		</wakeupNote>
		<inclusionNote>
			<lang xml:lang="en">Tripple Press little button on device</lang>
		</inclusionNote>
		<productName>FGS-213</productName>
		<brandName>Fibaro</brandName>
		<productLine>Fibaro</productLine>
		<productVersion>3.2</productVersion>
	</deviceDescription>

	<commandClasses>
		<commandClass id="0027" />
		<commandClass id="0022" />
		<commandClass id="0059" />
		<commandClass id="0085" version="2"/>
		<commandClass id="0020" />
		<commandClass id="005b" version="2" />
		<commandClass id="0070" />
		<commandClass id="0056" />
		<commandClass id="005a" />
		<commandClass id="007a" version="3" />
		<commandClass id="0072" version="2" />
		<commandClass id="0032" version="3" />
		<commandClass id="0060" version="4" controlled="true"/>
		<commandClass id="008E" version="3" />
		<commandClass id="0071" version="5" />
		<commandClass id="0073" />
		<commandClass id="0075" version="2" />
		<commandClass id="0098" />
		<commandClass id="0025" controlled="true" />
		<commandClass id="0086" version="2" />
		<commandClass id="005E" version="2" />

	</commandClasses>

	<assocGroups>
		<assocGroup number="1" maxNodes="1">
			<description>
				<lang xml:lang="en">"Lifeline" reports the device status and allows for assigning single device only (main controller by default).</lang>
			</description>
		</assocGroup>
		<assocGroup number="2" maxNodes="5">
			<description>
				<lang xml:lang="en">"On/Off (S1)" is assigned to switch connected to the S1 terminal (uses Basic command class).</lang>
			</description>
		</assocGroup>
		<assocGroup number="3" maxNodes="5">
			<description>
				<lang xml:lang="en">"Dimmer (S1)" is assigned to switch connected to the S1 terminal (uses Switch Multilevel command class).</lang>
			</description>
		</assocGroup>
		<assocGroup number="4" maxNodes="5">
			<description>
				<lang xml:lang="en">"On/Off (S2)" is assigned to switch connected to the S2 terminal (uses Basic command class).</lang>
			</description>
		</assocGroup>
		<assocGroup number="5" maxNodes="5">
			<description>
				<lang xml:lang="en">"Dimmer (S2)" is assigned to switch connected to the S2 terminal (uses Switch Multilevel command class).</lang>
			</description>
		</assocGroup>
	</assocGroups>


</ZWaveDevice>
